wechat_copilot/main.py
wechat_copilot/accessibility/util.py
wechat_copilot/accessibility/wechat_reader.py
wechat_copilot/ai/gpt_client.py
wechat_copilot/config/settings.py
wechat_copilot/hotkey/shortcut_manager.py
wechat_copilot/ui/suggestion_window.py
wechat_copilot-0.0.1.dist-info/METADATA
wechat_copilot-0.0.1.dist-info/WHEEL
wechat_copilot-0.0.1.dist-info/entry_points.txt
wechat_copilot-0.0.1.dist-info/RECORD
