Metadata-Version: 2.4
Name: wechat-copilot
Version: 0.0.1
Summary: 自动解析微信窗口的聊天内容,结合AI大模型，生成回复建议。
Project-URL: Homepage, https://github.com/saifeiLee/wechat-copilot
Project-URL: Repository, https://github.com/saifeiLee/wechat-copilot.git
Author-email: lisaifei <waltermitty121906@gmail.com>
License: MIT
Classifier: Development Status :: 3 - Alpha
Classifier: License :: OSI Approved :: MIT License
Classifier: Operating System :: MacOS :: MacOS X
Classifier: Programming Language :: Python :: 3
Requires-Python: >=3.8
Requires-Dist: openai>=1.63.2
Requires-Dist: pydantic>=2.10.4
Requires-Dist: pynput>=1.7.7
Requires-Dist: pyobjc>=11.0.0
Requires-Dist: pyperclip>=1.9.0
Requires-Dist: python-dotenv>=1.0.1
Requires-Dist: rumps>=0.4.0
